hyper/__init__.py
hyper/certs.pem
hyper/cli.py
hyper/compat.py
hyper/contrib.py
hyper/httplib_compat.py
hyper/ssl_compat.py
hyper/tls.py
hyper/common/__init__.py
hyper/common/bufsocket.py
hyper/common/connection.py
hyper/common/decoder.py
hyper/common/exceptions.py
hyper/common/headers.py
hyper/common/util.py
hyper/http11/__init__.py
hyper/http11/connection.py
hyper/http11/parser.py
hyper/http11/response.py
hyper/http20/__init__.py
hyper/http20/connection.py
hyper/http20/errors.py
hyper/http20/exceptions.py
hyper/http20/response.py
hyper/http20/stream.py
hyper/http20/util.py
hyper/http20/window.py
hypertemp/__init__.py
hypertemp/certs.pem
hypertemp/cli.py
hypertemp/compat.py
hypertemp/contrib.py
hypertemp/httplib_compat.py
hypertemp/ssl_compat.py
hypertemp/tls.py
hypertemp/common/__init__.py
hypertemp/common/bufsocket.py
hypertemp/common/connection.py
hypertemp/common/decoder.py
hypertemp/common/exceptions.py
hypertemp/common/headers.py
hypertemp/common/util.py
hypertemp/http11/__init__.py
hypertemp/http11/connection.py
hypertemp/http11/parser.py
hypertemp/http11/response.py
hypertemp/http20/__init__.py
hypertemp/http20/connection.py
hypertemp/http20/errors.py
hypertemp/http20/exceptions.py
hypertemp/http20/response.py
hypertemp/http20/stream.py
hypertemp/http20/util.py
hypertemp/http20/window.py
hypertemp-0.8.0.dist-info/DESCRIPTION.rst
hypertemp-0.8.0.dist-info/METADATA
hypertemp-0.8.0.dist-info/RECORD
hypertemp-0.8.0.dist-info/WHEEL
hypertemp-0.8.0.dist-info/entry_points.txt
hypertemp-0.8.0.dist-info/metadata.json
hypertemp-0.8.0.dist-info/top_level.txt
