Metadata-Version: 2.0
Name: hypertemp
Version: 0.8.0
Summary: HTTP/2 Client for Python
Home-page: http://hyper.rtfd.org
Author: Cory Benfield
Author-email: cory@lukasa.co.uk
License: MIT License
Platform: UNKNOWN
Classifier: Development Status :: 3 - Alpha
Classifier: Intended Audience :: Developers
Classifier: License :: OSI Approved :: MIT License
Classifier: Programming Language :: Python
Classifier: Programming Language :: Python :: 2
Classifier: Programming Language :: Python :: 2.7
Classifier: Programming Language :: Python :: 3
Classifier: Programming Language :: Python :: 3.4
Classifier: Programming Language :: Python :: 3.5
Classifier: Programming Language :: Python :: Implementation :: CPython
Requires-Dist: h2 (!=2.5.0,<3.0,>=2.4)
Requires-Dist: hyperframe (<4.0,>=3.2)
Requires-Dist: rfc3986 (<2.0,>=1.1.0)
Requires-Dist: brotlipy (<1.0,>=0.7.0)
Requires-Dist: cryptography (<1.0); platform_python_implementation == "PyPy" and python_full_version < "2.7.9"
Requires-Dist: pyOpenSSL (>=0.15); python_full_version < "2.7.9"
Requires-Dist: service-identity (>=14.0.0); python_full_version < "2.7.9"
Requires-Dist: enum34 (<2,>=1.0.4); python_version == "2.7" or python_version == "3.3"
Provides-Extra: fast
Requires-Dist: pycohttpparser; extra == 'fast'
